aiscpy/__init__.py
aiscpy/core.py
aiscpy/design.py
aiscpy/info.py
aiscpy/main.py
aiscpy/shape.py
aiscpy/shapes_AISC.db
aiscpy/test/__init__.py
aiscpy/test/test_core.py
aiscpy/test/test_design.py
aiscpy/test/test_info.py
aiscpy/test/test_main.py
aiscpy/test/test_shape_py.py
aiscpy-0.1.5.dist-info/LICENSE
aiscpy-0.1.5.dist-info/METADATA
aiscpy-0.1.5.dist-info/WHEEL
aiscpy-0.1.5.dist-info/top_level.txt
aiscpy-0.1.5.dist-info/RECORD
