Metadata-Version: 2.1
Name: aiscpy
Version: 0.1.5
Summary: Gestor de consultas para perfiles de acero AISC
Author: Rodrigo Jimenez
Author-email: jimenezhuancarodrigo@gmail.com
Maintainer: Rodrigo Jimenez
Maintainer-email: jimenezhuancarodrigo@gmail.com
License: GNU General Public License v3 (GPLv3)
Keywords: steel,AISC,engineering,shapes_AISC
Platform: UNKNOWN
Requires-Python: >=3
License-File: LICENSE
